apysc/__init__.py
apysc/_animation/__init__.py
apysc/_animation/animation_base.py
apysc/_animation/animation_cx.py
apysc/_animation/animation_cx_mixin.py
apysc/_animation/animation_cy.py
apysc/_animation/animation_cy_mixin.py
apysc/_animation/animation_fill_alpha.py
apysc/_animation/animation_fill_alpha_mixin.py
apysc/_animation/animation_fill_color.py
apysc/_animation/animation_fill_color_mixin.py
apysc/_animation/animation_finish_mixin.py
apysc/_animation/animation_height.py
apysc/_animation/animation_height_for_ellipse.py
apysc/_animation/animation_height_for_ellipse_mixin.py
apysc/_animation/animation_height_mixin.py
apysc/_animation/animation_line_alpha.py
apysc/_animation/animation_line_alpha_mixin.py
apysc/_animation/animation_line_color.py
apysc/_animation/animation_line_color_mixin.py
apysc/_animation/animation_line_thickness.py
apysc/_animation/animation_line_thickness_mixin.py
apysc/_animation/animation_mixins.py
apysc/_animation/animation_move.py
apysc/_animation/animation_move_mixin.py
apysc/_animation/animation_parallel.py
apysc/_animation/animation_parallel_mixin.py
apysc/_animation/animation_pause_mixin.py
apysc/_animation/animation_play_mixin.py
apysc/_animation/animation_radius.py
apysc/_animation/animation_radius_mixin.py
apysc/_animation/animation_reset_mixin.py
apysc/_animation/animation_reverse_mixin.py
apysc/_animation/animation_rotation_around_center.py
apysc/_animation/animation_rotation_around_center_mixin.py
apysc/_animation/animation_rotation_around_point.py
apysc/_animation/animation_rotation_around_point_mixin.py
apysc/_animation/animation_scale_x_from_center.py
apysc/_animation/animation_scale_x_from_center_mixin.py
apysc/_animation/animation_scale_x_from_point.py
apysc/_animation/animation_scale_x_from_point_mixin.py
apysc/_animation/animation_scale_y_from_center.py
apysc/_animation/animation_scale_y_from_center_mixin.py
apysc/_animation/animation_scale_y_from_point.py
apysc/_animation/animation_scale_y_from_point_mixin.py
apysc-4.10.2.dist-info/LICENSE
apysc-4.10.2.dist-info/METADATA
apysc-4.10.2.dist-info/WHEEL
apysc-4.10.2.dist-info/top_level.txt
apysc-4.10.2.dist-info/RECORD
