Metadata-Version: 2.1
Name: apysc
Version: 4.10.2
Summary: apysc is the Python's frontend library to create html and js file, that has the ActionScript 3 (as3)-like interface.
Home-page: https://github.com/simon-ritchie/apysc
Maintainer: simon-ritchie
Maintainer-email: 
License: MIT
Platform: UNKNOWN
Classifier: Programming Language :: Python :: 3
Classifier: Programming Language :: Python :: 3.8
Classifier: Programming Language :: Python :: 3.9
Classifier: Programming Language :: Python :: 3.10
Classifier: Programming Language :: Python :: 3.11
Classifier: License :: OSI Approved :: MIT License
License-File: LICENSE
Requires-Dist: typing-extensions
Requires-Dist: html-minifier
